{
  "_class": "shapeGroup",
  "clippingMaskMode": 0,
  "do_objectID": "319E1B41-4A3F-4D1B-8F21-415936C46B0D",
  "exportOptions": {
    "_class": "exportOptions",
    "exportFormats": [
    ],
    "includedLayerIds": [
    ],
    "layerOptions": 0,
    "shouldTrim": false
  },
  "frame": {
    "_class": "rect",
    "constrainProportions": false,
    "height": 8.546,
    "width": 7.325142857142854,
    "x": 22.07717142857109,
    "y": -0.0003399999999942338
  },
  "hasClickThrough": false,
  "hasClippingMask": false,
  "isFlippedHorizontal": false,
  "isFlippedVertical": false,
  "isLocked": false,
  "isVisible": true,
  "layerListExpandedType": 1,
  "layers": [
    {
      "class": "shapePath",
      "id": "BD86F20C-15AE-42F8-96E1-12142545A72B"
    },
    {
      "class": "shapePath",
      "id": "624E5D63-B561-4F86-B9CB-F6E5D10EBE8E"
    }
  ],
  "name": "Fill 7",
  "nameIsFixed": false,
  "resizingConstraint": 63,
  "resizingType": 0,
  "rotation": 0,
  "shouldBreakMaskChain": false,
  "style": {
    "_class": "style",
    "endDecorationType": 0,
    "fills": [
      {
        "_class": "fill",
        "color": {
          "_class": "color",
          "alpha": 1,
          "blue": 0.4487138605442177,
          "green": 0.4487138605442177,
          "red": 0.4487138605442177
        },
        "fillType": 0,
        "isEnabled": true,
        "noiseIndex": 0,
        "noiseIntensity": 0,
        "patternFillType": 1,
        "patternTileScale": 1
      }
    ],
    "miterLimit": 10,
    "startDecorationType": 0
  },
  "windingRule": 1
}