{
  "_class": "artboard",
  "backgroundColor": {
    "_class": "color",
    "alpha": 1,
    "blue": 1,
    "green": 1,
    "red": 1
  },
  "booleanOperation": -1,
  "do_objectID": "86D53281-270D-439C-8B36-1EDAE740B782",
  "exportOptions": {
    "_class": "exportOptions",
    "do_objectID": "1B9D3FCA-0D66-488C-BED9-FD649F5934BA",
    "exportFormats": [
    ],
    "includedLayerIds": [
    ],
    "layerOptions": 0,
    "shouldTrim": false
  },
  "frame": {
    "_class": "rect",
    "constrainProportions": false,
    "do_objectID": "A1045EAA-B200-4071-9D27-A979EF1A65AF",
    "height": 812,
    "width": 375,
    "x": 789,
    "y": -406
  },
  "hasBackgroundColor": true,
  "hasClickThrough": true,
  "horizontalRulerData": {
    "_class": "rulerData",
    "base": 0,
    "do_objectID": "AA464D61-D718-4C39-AEB8-213B19F0833E",
    "guides": [
    ]
  },
  "includeBackgroundColorInExport": true,
  "includeInCloudUpload": true,
  "isFixedToViewport": false,
  "isFlippedHorizontal": false,
  "isFlippedVertical": false,
  "isFlowHome": false,
  "isLocked": false,
  "isVisible": true,
  "layerListExpandedType": 2,
  "layers": [
    {
      "class": "symbolInstance",
      "id": "96985A54-08BD-42FD-B1D5-08715C135246"
    },
    {
      "class": "symbolInstance",
      "id": "0BEDBC2F-1797-46A6-9A5D-4F499F72DE9E"
    },
    {
      "class": "symbolInstance",
      "id": "A9461343-5372-49B9-B74D-E44B1202F1F6"
    },
    {
      "class": "symbolInstance",
      "id": "E895291E-94EB-44C5-BADA-DF1D500FAB97"
    },
    {
      "class": "symbolInstance",
      "id": "F3B2FBF0-3F23-4238-98BF-5A4693E90A8E"
    },
    {
      "class": "symbolInstance",
      "id": "192EF4D4-AD8D-4B97-998F-CB092D6C753C"
    },
    {
      "class": "symbolInstance",
      "id": "2946BAB2-E8D4-4292-AAC3-1DA5D2AEECFC"
    },
    {
      "class": "symbolInstance",
      "id": "8A2C0C9F-6063-4A64-A812-6E531783F4D7"
    }
  ],
  "name": "[iPhone X] / store / window / product-review",
  "nameIsFixed": true,
  "presetDictionary": {
    "allowResizedMatching": 1,
    "height": 812,
    "name": "iPhone X",
    "offersLandscapeVariant": 1,
    "width": 375
  },
  "resizesContent": false,
  "resizingConstraint": 63,
  "resizingType": 0,
  "rotation": 0,
  "shouldBreakMaskChain": true,
  "style": {
    "_class": "style",
    "do_objectID": "1450F0F6-DAE7-407A-8373-5867F996BD57",
    "endMarkerType": 0,
    "miterLimit": 10,
    "startMarkerType": 0,
    "windingRule": 1
  },
  "verticalRulerData": {
    "_class": "rulerData",
    "base": 0,
    "do_objectID": "60528A22-1D82-4724-88BB-4DF90A42B81E",
    "guides": [
    ]
  }
}