{
  "_class": "symbolMaster",
  "backgroundColor": {
    "_class": "color",
    "alpha": 1,
    "blue": 0.2,
    "do_objectID": "C9A6BCB5-CFA7-448A-9604-C0053E0F6676",
    "green": 0.2,
    "red": 0.2
  },
  "booleanOperation": 0,
  "changeIdentifier": 5188,
  "do_objectID": "69338C1E-A410-4224-86E8-E6CB820297AC",
  "exportOptions": {
    "_class": "exportOptions",
    "do_objectID": "A0C58A6E-6665-42E3-8DF9-AEF595AB98DA",
    "exportFormats": [
      {
        "_class": "exportFormat",
        "absoluteSize": 0,
        "fileFormat": "png",
        "name": "mdpi/",
        "namingScheme": 1,
        "scale": 1,
        "visibleScaleType": 0
      },
      {
        "_class": "exportFormat",
        "absoluteSize": 0,
        "fileFormat": "png",
        "name": "hdpi/",
        "namingScheme": 1,
        "scale": 1.5,
        "visibleScaleType": 0
      },
      {
        "_class": "exportFormat",
        "absoluteSize": 0,
        "fileFormat": "png",
        "name": "xhdpi/",
        "namingScheme": 1,
        "scale": 2,
        "visibleScaleType": 0
      },
      {
        "_class": "exportFormat",
        "absoluteSize": 0,
        "fileFormat": "png",
        "name": "xxhdpi/",
        "namingScheme": 1,
        "scale": 3,
        "visibleScaleType": 0
      },
      {
        "_class": "exportFormat",
        "absoluteSize": 0,
        "fileFormat": "png",
        "name": "xxxhdpi/",
        "namingScheme": 1,
        "scale": 4,
        "visibleScaleType": 0
      }
    ],
    "includedLayerIds": [
    ],
    "layerOptions": 0,
    "shouldTrim": false
  },
  "frame": {
    "_class": "rect",
    "constrainProportions": false,
    "do_objectID": "F2A656C7-586F-4CA6-BEB3-502BFCE5BFA4",
    "height": 48,
    "width": 256,
    "x": 5334,
    "y": 3516
  },
  "hasBackgroundColor": false,
  "hasClickThrough": true,
  "horizontalRulerData": {
    "_class": "rulerData",
    "base": 0,
    "do_objectID": "55EBB5F9-92AF-4B70-9C23-1F9FBDC2DE65",
    "guides": [
    ]
  },
  "includeBackgroundColorInExport": false,
  "includeBackgroundColorInInstance": false,
  "includeInCloudUpload": true,
  "isFixedToViewport": false,
  "isFlippedHorizontal": false,
  "isFlippedVertical": false,
  "isFlowHome": false,
  "isLocked": false,
  "isVisible": true,
  "layerListExpandedType": 2,
  "layers": [
    {
      "class": "shapeGroup",
      "id": "AE796E52-E477-4406-A678-0DC63E853E5D"
    },
    {
      "class": "text",
      "id": "3D249F67-2E46-4382-B1DB-A4940DB0AE26"
    }
  ],
  "name": "store / toast / cart-btn",
  "nameIsFixed": true,
  "resizesContent": true,
  "resizingConstraint": 63,
  "resizingType": 0,
  "rotation": 0,
  "shouldBreakMaskChain": true,
  "style": {
    "_class": "style",
    "do_objectID": "E7CFC351-D0B5-4586-AF94-2B405BDDE627",
    "endMarkerType": 0,
    "miterLimit": 10,
    "startMarkerType": 0,
    "windingRule": 1
  },
  "symbolID": "CC8C8E3E-C18D-4ACC-8F56-AE85C6B4EC15",
  "verticalRulerData": {
    "_class": "rulerData",
    "base": 0,
    "do_objectID": "B2311EE7-199C-4649-9EF7-9248F5C537F2",
    "guides": [
    ]
  }
}