{
  "_class": "shapePath",
  "booleanOperation": -1,
  "clippingMaskMode": 0,
  "do_objectID": "523CB37A-03CF-4CDA-B8FD-54958BD63FAE",
  "edited": true,
  "exportOptions": {
    "_class": "exportOptions",
    "exportFormats": [
    ],
    "includedLayerIds": [
    ],
    "layerOptions": 0,
    "shouldTrim": false
  },
  "frame": {
    "_class": "rect",
    "constrainProportions": false,
    "height": 13.35689599498671,
    "width": 13.96615531690726,
    "x": 19.92309880343753,
    "y": 0.00001364664641534397
  },
  "hasClippingMask": false,
  "isClosed": true,
  "isFixedToViewport": false,
  "isFlippedHorizontal": false,
  "isFlippedVertical": false,
  "isLocked": false,
  "isVisible": true,
  "layerListExpandedType": 1,
  "name": "Shape",
  "nameIsFixed": false,
  "pointRadiusBehaviour": 1,
  "points": [
    {
      "_class": "curvePoint",
      "cornerRadius": 0,
      "curveFrom": "{0.54791013689349488, 0.03118956144525999}",
      "curveMode": 4,
      "curveTo": "{0.52826107322686144, -0.010408800944365922}",
      "hasCurveFrom": false,
      "hasCurveTo": true,
      "point": "{0.54791013689349488, 0.03118956144525999}"
    },
    {
      "_class": "curvePoint",
      "cornerRadius": 0,
      "curveFrom": "{0.66881178890046367, 0.2871586972596924}",
      "curveMode": 4,
      "curveTo": "{0.66101168231936913, 0.27064218211404761}",
      "hasCurveFrom": true,
      "hasCurveTo": false,
      "point": "{0.66101168231936913, 0.27064218211404761}"
    },
    {
      "_class": "curvePoint",
      "cornerRadius": 0,
      "curveFrom": "{0.70132789585297961, 0.30125137081728021}",
      "curveMode": 4,
      "curveTo": "{0.68388729609786081, 0.2986064355708532}",
      "hasCurveFrom": false,
      "hasCurveTo": true,
      "point": "{0.70132789585297961, 0.30125137081728021}"
    },
    {
      "_class": "curvePoint",
      "cornerRadius": 0,
      "curveFrom": "{0.99800604606544285, 0.34623983596858038}",
      "curveMode": 4,
      "curveTo": "{0.95409520510138801, 0.33958246025543742}",
      "hasCurveFrom": true,
      "hasCurveTo": false,
      "point": "{0.95409520510138801, 0.33958246025543742}"
    },
    {
      "_class": "curvePoint",
      "cornerRadius": 0,
      "curveFrom": "{0.9837841649898722, 0.43504578874722072}",
      "curveMode": 4,
      "curveTo": "{1.0155484544405953, 0.40265966212301391}",
      "hasCurveFrom": false,
      "hasCurveTo": true,
      "point": "{0.9837841649898722, 0.43504578874722072}"
    },
    {
      "_class": "curvePoint",
      "cornerRadius": 0,
      "curveFrom": "{0.78831161452388254, 0.63438219340286306}",
      "curveMode": 4,
      "curveTo": "{0.80092805197583394, 0.62151781794733119}",
      "hasCurveFrom": true,
      "hasCurveTo": false,
      "point": "{0.80092805197583394, 0.62151781794733119}"
    },
    {
      "_class": "curvePoint",
      "cornerRadius": 0,
      "curveFrom": "{0.78554711891833384, 0.67106736338426554}",
      "curveMode": 4,
      "curveTo": "{0.78256334320809551, 0.65291311743587954}",
      "hasCurveFrom": false,
      "hasCurveTo": true,
      "point": "{0.78554711891833384, 0.67106736338426554}"
    },
    {
      "_class": "curvePoint",
      "cornerRadius": 0,
      "curveFrom": "{0.83630263172162211, 0.98000071335934746}",
      "curveMode": 4,
      "curveTo": "{0.8287922881360098, 0.93427526934681382}",
      "hasCurveFrom": true,
      "hasCurveTo": false,
      "point": "{0.8287922881360098, 0.93427526934681382}"
    },
    {
      "_class": "curvePoint",
      "cornerRadius": 0,
      "curveFrom": "{0.75113580534671687, 0.99329908747760598}",
      "curveMode": 4,
      "curveTo": "{0.79041043838305236, 1.0148761908037209}",
      "hasCurveFrom": false,
      "hasCurveTo": true,
      "point": "{0.75113580534671687, 0.99329908747760598}"
    },
    {
      "_class": "curvePoint",
      "cornerRadius": 0,
      "curveFrom": "{0.50942647852050293, 0.86052006264536496}",
      "curveMode": 4,
      "curveTo": "{0.52502669168269256, 0.86908539474370139}",
      "hasCurveFrom": true,
      "hasCurveTo": false,
      "point": "{0.52502669168269256, 0.86908539474370139}"
    },
    {
      "_class": "curvePoint",
      "cornerRadius": 0,
      "curveFrom": "{0.47520311932433429, 0.86910177205172878}",
      "curveMode": 4,
      "curveTo": "{0.49079550105421338, 0.86052006264536496}",
      "hasCurveFrom": false,
      "hasCurveTo": true,
      "point": "{0.47520311932433429, 0.86910177205172878}"
    },
    {
      "_class": "curvePoint",
      "cornerRadius": 0,
      "curveFrom": "{0.20988985551476738, 1.0150399638839951}",
      "curveMode": 4,
      "curveTo": "{0.24915665711879273, 0.99343829459583899}",
      "hasCurveFrom": true,
      "hasCurveTo": false,
      "point": "{0.24915665711879273, 0.99343829459583899}"
    },
    {
      "_class": "curvePoint",
      "cornerRadius": 0,
      "curveFrom": "{0.1714688486002586, 0.93445541973511548}",
      "curveMode": 4,
      "curveTo": "{0.16398199931157714, 0.98018086374764912}",
      "hasCurveFrom": false,
      "hasCurveTo": true,
      "point": "{0.1714688486002586, 0.93445541973511548}"
    },
    {
      "_class": "curvePoint",
      "cornerRadius": 0,
      "curveFrom": "{0.21755682774658655, 0.65306870186214006}",
      "curveMode": 4,
      "curveTo": "{0.21458088346865886, 0.67122294781052594}",
      "hasCurveFrom": true,
      "hasCurveTo": false,
      "point": "{0.21458088346865886, 0.67122294781052594}"
    },
    {
      "_class": "curvePoint",
      "cornerRadius": 0,
      "curveFrom": "{0.19917645611422763, 0.62168159102760534}",
      "curveMode": 4,
      "curveTo": "{0.21179289356617925, 0.63453777782912357}",
      "hasCurveFrom": false,
      "hasCurveTo": true,
      "point": "{0.19917645611422763, 0.62168159102760534}"
    },
    {
      "_class": "curvePoint",
      "cornerRadius": 0,
      "curveFrom": "{-0.015545754970567939, 0.40294626501349373}",
      "curveMode": 4,
      "curveTo": "{0.016234197344775943, 0.4353160143296731}",
      "hasCurveFrom": true,
      "hasCurveTo": false,
      "point": "{0.016234197344775943, 0.4353160143296731}"
    },
    {
      "_class": "curvePoint",
      "cornerRadius": 0,
      "curveFrom": "{0.045876168639398099, 0.33983630852986252}",
      "curveMode": 4,
      "curveTo": "{0.0019731591076539014, 0.34651825020504645}",
      "hasCurveFrom": false,
      "hasCurveTo": true,
      "point": "{0.045876168639398099, 0.33983630852986252}"
    },
    {
      "_class": "curvePoint",
      "cornerRadius": 0,
      "curveFrom": "{0.31606058334599396, 0.29871288807303154}",
      "curveMode": 4,
      "curveTo": "{0.29862781502318581, 0.30136601197347224}",
      "hasCurveFrom": true,
      "hasCurveTo": false,
      "point": "{0.29862781502318581, 0.30136601197347224}"
    },
    {
      "_class": "curvePoint",
      "cornerRadius": 0,
      "curveFrom": "{0.33892836569217533, 0.2707322573081985}",
      "curveMode": 4,
      "curveTo": "{0.33113609054339105, 0.28725696110785698}",
      "hasCurveFrom": false,
      "hasCurveTo": true,
      "point": "{0.33892836569217533, 0.2707322573081985}"
    },
    {
      "_class": "curvePoint",
      "cornerRadius": 0,
      "curveFrom": "{0.47152234613847632, -0.010392423636338504}",
      "curveMode": 4,
      "curveTo": "{0.45190460820108397, 0.03121412740730127}",
      "hasCurveFrom": true,
      "hasCurveTo": false,
      "point": "{0.45190460820108397, 0.03121412740730127}"
    }
  ],
  "resizingConstraint": 63,
  "resizingType": 0,
  "rotation": 0,
  "shouldBreakMaskChain": false,
  "style": {
    "_class": "style",
    "blur": {
      "_class": "blur",
      "center": "{0.5, 0.5}",
      "isEnabled": false,
      "motionAngle": 0,
      "radius": 1.09375,
      "saturation": 1,
      "type": 0
    },
    "endMarkerType": 0,
    "fills": [
      {
        "_class": "fill",
        "color": {
          "_class": "color",
          "alpha": 1,
          "blue": 0.0980392156862745,
          "green": 0.7450980392156863,
          "red": 1
        },
        "fillType": 0,
        "isEnabled": true,
        "noiseIndex": 0,
        "noiseIntensity": 0,
        "patternFillType": 1,
        "patternTileScale": 1
      }
    ],
    "miterLimit": 10,
    "startMarkerType": 0,
    "windingRule": 0
  }
}