{
  "_class": "symbolInstance",
  "do_objectID": "14CF494E-5AD1-4EFB-A60E-F85ACA406393",
  "exportOptions": {
    "_class": "exportOptions",
    "do_objectID": "75143E6D-ECF5-4215-A5A2-4494B15C9C10",
    "exportFormats": [
      {
        "_class": "exportFormat",
        "absoluteSize": 0,
        "fileFormat": "png",
        "name": "mdpi/",
        "namingScheme": 1,
        "scale": 1,
        "visibleScaleType": 0
      },
      {
        "_class": "exportFormat",
        "absoluteSize": 0,
        "fileFormat": "png",
        "name": "hdpi/",
        "namingScheme": 1,
        "scale": 1.5,
        "visibleScaleType": 0
      },
      {
        "_class": "exportFormat",
        "absoluteSize": 0,
        "fileFormat": "png",
        "name": "xhdpi/",
        "namingScheme": 1,
        "scale": 2,
        "visibleScaleType": 0
      },
      {
        "_class": "exportFormat",
        "absoluteSize": 0,
        "fileFormat": "png",
        "name": "xxhdpi/",
        "namingScheme": 1,
        "scale": 3,
        "visibleScaleType": 0
      },
      {
        "_class": "exportFormat",
        "absoluteSize": 0,
        "fileFormat": "png",
        "name": "xxxhdpi/",
        "namingScheme": 1,
        "scale": 4,
        "visibleScaleType": 0
      }
    ],
    "includedLayerIds": [
    ],
    "layerOptions": 0,
    "shouldTrim": false
  },
  "frame": {
    "_class": "rect",
    "constrainProportions": false,
    "do_objectID": "ECE1502E-E374-469E-BFC4-A349099FC1FE",
    "height": 48,
    "width": 320,
    "x": 0,
    "y": 20
  },
  "horizontalSpacing": 0,
  "isFlippedHorizontal": false,
  "isFlippedVertical": false,
  "isLocked": false,
  "isVisible": true,
  "layerListExpandedType": 0,
  "name": "header / center-text-4char",
  "nameIsFixed": false,
  "overrideValues": [
    {
      "_class": "overrideValue",
      "do_objectID": "E46834F2-9256-4DD7-A516-90D133EB5929",
      "overrideName": "181587AB-F1E9-4BF5-A893-2C0A3144AF61_stringValue",
      "value": "선택완료"
    },
    {
      "_class": "overrideValue",
      "do_objectID": "17CA8C73-8790-4E84-91C3-5B05985B32FB",
      "overrideName": "9CC620A2-F359-4C76-BDF7-49AA5F08FA92_stringValue",
      "value": "3장의 사진선택"
    }
  ],
  "resizingConstraint": 63,
  "resizingType": 0,
  "rotation": 0,
  "scale": 1,
  "shouldBreakMaskChain": false,
  "style": {
    "_class": "style",
    "do_objectID": "F1EFCF49-0116-453B-8255-464425CAA023",
    "endDecorationType": 0,
    "miterLimit": 10,
    "startDecorationType": 0
  },
  "symbolID": "7D00F393-37DD-4201-9E38-0B405F875A58",
  "verticalSpacing": 0
}