{
  "_class": "symbolInstance",
  "booleanOperation": 0,
  "clippingMaskMode": 0,
  "do_objectID": "254BB135-236D-49F7-9293-3C78C679F16B",
  "exportOptions": {
    "_class": "exportOptions",
    "do_objectID": "9F5DC7B5-82C1-4EBD-9837-7191305D4B38",
    "exportFormats": [
      {
        "_class": "exportFormat",
        "absoluteSize": 0,
        "fileFormat": "png",
        "name": "mdpi/",
        "namingScheme": 1,
        "scale": 1,
        "visibleScaleType": 0
      },
      {
        "_class": "exportFormat",
        "absoluteSize": 0,
        "fileFormat": "png",
        "name": "hdpi/",
        "namingScheme": 1,
        "scale": 1.5,
        "visibleScaleType": 0
      },
      {
        "_class": "exportFormat",
        "absoluteSize": 0,
        "fileFormat": "png",
        "name": "xhdpi/",
        "namingScheme": 1,
        "scale": 2,
        "visibleScaleType": 0
      },
      {
        "_class": "exportFormat",
        "absoluteSize": 0,
        "fileFormat": "png",
        "name": "xxhdpi/",
        "namingScheme": 1,
        "scale": 3,
        "visibleScaleType": 0
      },
      {
        "_class": "exportFormat",
        "absoluteSize": 0,
        "fileFormat": "png",
        "name": "xxxhdpi/",
        "namingScheme": 1,
        "scale": 4,
        "visibleScaleType": 0
      }
    ],
    "includedLayerIds": [
    ],
    "layerOptions": 0,
    "shouldTrim": false
  },
  "frame": {
    "_class": "rect",
    "constrainProportions": false,
    "do_objectID": "8748F2AB-71F7-4D97-A169-383DB5831759",
    "height": 48,
    "width": 320,
    "x": 0,
    "y": 108
  },
  "hasClippingMask": false,
  "horizontalSpacing": 0,
  "isFixedToViewport": false,
  "isFlippedHorizontal": false,
  "isFlippedVertical": false,
  "isLocked": false,
  "isVisible": true,
  "layerListExpandedType": 0,
  "name": "store / product / accordion-menu-sub",
  "nameIsFixed": true,
  "overrideValues": [
    {
      "_class": "overrideValue",
      "do_objectID": "E6C6C138-D893-4AAA-8D5A-1EDCF86BC52A",
      "overrideName": "71400AAB-159A-4C60-9266-B78245E1122C_symbolID",
      "value": "F8712283-CA29-40B2-AA23-2FDED4DE5945"
    },
    {
      "_class": "overrideValue",
      "do_objectID": "10D1073D-B67E-4891-8960-BF259AC7FB67",
      "overrideName": "3DD30F37-E397-4CC0-BC3F-0A386833C9CC_stringValue",
      "value": "구매후기"
    }
  ],
  "resizingConstraint": 36,
  "resizingType": 0,
  "rotation": 0,
  "scale": 1,
  "shouldBreakMaskChain": false,
  "style": {
    "_class": "style",
    "do_objectID": "E75A3236-CD1C-483F-85E8-2E3C6B48F4BA",
    "endMarkerType": 0,
    "miterLimit": 10,
    "startMarkerType": 0,
    "windingRule": 1
  },
  "symbolID": "09D1E94C-B074-4259-AC36-D75CC43E1CC7",
  "verticalSpacing": 0
}