{
  "_class": "symbolMaster",
  "backgroundColor": {
    "_class": "color",
    "alpha": 1,
    "blue": 1,
    "do_objectID": "B8282108-160F-4108-8523-6F5602CB465B",
    "green": 1,
    "red": 1
  },
  "booleanOperation": 0,
  "changeIdentifier": 4005,
  "do_objectID": "A41824B0-285C-460B-81BB-9DCAE7796D12",
  "exportOptions": {
    "_class": "exportOptions",
    "do_objectID": "8D4C63F5-E26C-45FD-B20F-04AA1B77661F",
    "exportFormats": [
      {
        "_class": "exportFormat",
        "absoluteSize": 0,
        "fileFormat": "png",
        "name": "mdpi/",
        "namingScheme": 1,
        "scale": 1,
        "visibleScaleType": 0
      },
      {
        "_class": "exportFormat",
        "absoluteSize": 0,
        "fileFormat": "png",
        "name": "hdpi/",
        "namingScheme": 1,
        "scale": 1.5,
        "visibleScaleType": 0
      },
      {
        "_class": "exportFormat",
        "absoluteSize": 0,
        "fileFormat": "png",
        "name": "xhdpi/",
        "namingScheme": 1,
        "scale": 2,
        "visibleScaleType": 0
      },
      {
        "_class": "exportFormat",
        "absoluteSize": 0,
        "fileFormat": "png",
        "name": "xxhdpi/",
        "namingScheme": 1,
        "scale": 3,
        "visibleScaleType": 0
      },
      {
        "_class": "exportFormat",
        "absoluteSize": 0,
        "fileFormat": "png",
        "name": "xxxhdpi/",
        "namingScheme": 1,
        "scale": 4,
        "visibleScaleType": 0
      }
    ],
    "includedLayerIds": [
    ],
    "layerOptions": 0,
    "shouldTrim": false
  },
  "frame": {
    "_class": "rect",
    "constrainProportions": false,
    "do_objectID": "E4066FBA-8EFF-4854-A0AC-C73DD761641D",
    "height": 64,
    "width": 320,
    "x": 7302,
    "y": 954
  },
  "hasBackgroundColor": false,
  "hasClickThrough": false,
  "horizontalRulerData": {
    "_class": "rulerData",
    "base": 0,
    "do_objectID": "46C6817D-81A8-4D38-A0A3-B1D6E0F62E3B",
    "guides": [
    ]
  },
  "includeBackgroundColorInExport": true,
  "includeBackgroundColorInInstance": true,
  "includeInCloudUpload": true,
  "isFixedToViewport": false,
  "isFlippedHorizontal": false,
  "isFlippedVertical": false,
  "isFlowHome": false,
  "isLocked": false,
  "isVisible": true,
  "layerListExpandedType": 0,
  "layers": [
    {
      "class": "shapeGroup",
      "id": "4F446095-9DAD-4598-B38B-20CAEDAB708D"
    },
    {
      "class": "symbolInstance",
      "id": "962303BC-5D23-4B66-A653-B4CC825CA42F"
    }
  ],
  "name": "snackbar / body / error-2lines",
  "nameIsFixed": true,
  "resizesContent": true,
  "resizingConstraint": 63,
  "resizingType": 0,
  "rotation": 0,
  "shouldBreakMaskChain": true,
  "style": {
    "_class": "style",
    "do_objectID": "D9A86AB9-1D7C-4341-85DE-8C20C7018A54",
    "endMarkerType": 0,
    "miterLimit": 10,
    "startMarkerType": 0,
    "windingRule": 1
  },
  "symbolID": "C37FDD00-3F7E-4658-B6D0-1403114C42DC",
  "verticalRulerData": {
    "_class": "rulerData",
    "base": 0,
    "do_objectID": "4A54ECB1-8B51-4CCF-BD0D-936B9D1558D0",
    "guides": [
    ]
  }
}