{
  "_class": "artboard",
  "backgroundColor": {
    "_class": "color",
    "alpha": 1,
    "blue": 1,
    "do_objectID": "B178D54F-1DEF-4CA0-835D-4D73D62F17FC",
    "green": 1,
    "red": 1
  },
  "booleanOperation": 0,
  "do_objectID": "F54343B6-1222-429F-980E-B9184D9766AB",
  "exportOptions": {
    "_class": "exportOptions",
    "do_objectID": "E80209F0-DD53-482D-AC06-D3F3A69B332B",
    "exportFormats": [
    ],
    "includedLayerIds": [
    ],
    "layerOptions": 0,
    "shouldTrim": false
  },
  "frame": {
    "_class": "rect",
    "constrainProportions": false,
    "do_objectID": "B0D2A2AE-CF1B-442E-AD09-D78C2539262F",
    "height": 568,
    "width": 320,
    "x": 1277,
    "y": 1870
  },
  "hasBackgroundColor": true,
  "hasClickThrough": true,
  "horizontalRulerData": {
    "_class": "rulerData",
    "base": 0,
    "do_objectID": "069460D8-7B0A-4D7A-BDC0-98A21C9E14B1",
    "guides": [
    ]
  },
  "includeBackgroundColorInExport": true,
  "includeInCloudUpload": true,
  "isFixedToViewport": false,
  "isFlippedHorizontal": false,
  "isFlippedVertical": false,
  "isFlowHome": false,
  "isLocked": false,
  "isVisible": true,
  "layerListExpandedType": 2,
  "layers": [
    {
      "class": "symbolInstance",
      "id": "F3803E6E-008D-4E19-8469-D4C632DED321"
    },
    {
      "class": "symbolInstance",
      "id": "4CF68632-BB95-4469-A070-A804A1C453D5"
    },
    {
      "class": "symbolInstance",
      "id": "4E2BF200-751A-4767-8764-962A75685647"
    },
    {
      "class": "symbolInstance",
      "id": "817CE821-5D72-4BB4-9031-5206AAB48D64"
    },
    {
      "class": "symbolInstance",
      "id": "945EF363-94D2-4163-955C-80907592596F"
    },
    {
      "class": "symbolInstance",
      "id": "8C5381C7-C52D-43F1-85E9-257CE0D370C7"
    },
    {
      "class": "symbolInstance",
      "id": "F0CB6F30-C47D-4A16-8C9C-C8C300414E5C"
    },
    {
      "class": "symbolInstance",
      "id": "4C65B327-021E-468A-9011-59805297C62B"
    },
    {
      "class": "symbolInstance",
      "id": "14248E07-0E19-434F-B06C-6514A61F1C25"
    },
    {
      "class": "symbolInstance",
      "id": "62655F8E-6C81-460F-8FE0-0F4ECADB1F61"
    },
    {
      "class": "symbolInstance",
      "id": "0394BA4E-D303-4C0C-BAA5-BAA15CD6A0F2"
    },
    {
      "class": "symbolInstance",
      "id": "FEA95AF2-F297-48C0-B7D6-26FE66CD7E01"
    },
    {
      "class": "symbolInstance",
      "id": "89736983-D054-45A9-955A-670BDC15BB92"
    },
    {
      "class": "symbolInstance",
      "id": "7551C604-62F3-4304-8327-432C7EA03334"
    },
    {
      "class": "symbolInstance",
      "id": "15ECECA3-2F4D-4913-8A74-D181E76AFE10"
    },
    {
      "class": "symbolInstance",
      "id": "268F08EE-3A75-4632-AB55-35CDEDEBB2A9"
    },
    {
      "class": "symbolInstance",
      "id": "72DE9D0B-2097-47BA-B84A-A878451A6DD7"
    }
  ],
  "name": "store / add-to-cart-change-qty-error",
  "nameIsFixed": true,
  "presetDictionary": {
    "allowResizedMatching": 1,
    "height": 568,
    "name": "iPhone SE",
    "offersLandscapeVariant": 1,
    "width": 320
  },
  "resizesContent": false,
  "resizingConstraint": 63,
  "resizingType": 0,
  "rotation": 0,
  "shouldBreakMaskChain": true,
  "style": {
    "_class": "style",
    "do_objectID": "0E326AE3-B68D-4779-BF2B-4F1DBD65D3D1",
    "endMarkerType": 0,
    "miterLimit": 10,
    "startMarkerType": 0,
    "windingRule": 1
  },
  "verticalRulerData": {
    "_class": "rulerData",
    "base": 0,
    "do_objectID": "04315BDC-52A8-4DE6-A10B-BB8324A2FB30",
    "guides": [
    ]
  }
}